Metadata-Version: 1.1
Name: pyweaving
Version: 0.0.7
Summary: Python Weaving Tools
Home-page: https://github.com/storborg/pyweaving
Author: Scott Torborg
Author-email: storborg@gmail.com
License: MIT
Keywords: weaving handweaving wif draft pattern
Platform: UNKNOWN
Classifier: Development Status :: 2 - Pre-Alpha
Classifier: License :: OSI Approved :: MIT License
Classifier: Programming Language :: Python :: 2
Classifier: Programming Language :: Python :: 2.7
Classifier: Programming Language :: Python :: 3
Classifier: Programming Language :: Python :: 3.3
Classifier: Programming Language :: Python :: 3.4
Classifier: Programming Language :: Python :: 3.5
Classifier: Topic :: Multimedia :: Graphics
